dkist_header_validator/__init__.py
dkist_header_validator/base_validator.py
dkist_header_validator/exceptions.py
dkist_header_validator/spec_validators.py
dkist_header_validator/translator.py
dkist_header_validator/version.py
dkist_header_validator/api/__init__.py
dkist_header_validator/api/validate.py
dkist_header_validator/tests/__init__.py
dkist_header_validator/tests/conftest.py
dkist_header_validator/tests/test_base_validator.py
dkist_header_validator/tests/test_spec122_translation.py
dkist_header_validator/tests/test_spec122_validation+.py
dkist_header_validator/tests/test_spec122_validation-.py
dkist_header_validator/tests/test_spec214_validation+.py
dkist_header_validator/tests/test_spec214_validation-.py
dkist_header_validator/tests/test_translator.py
dkist_header_validator/utils/__init__.py
dkist_header_validator/utils/expansions.py
dkist_header_validator-5.2.1.dist-info/METADATA
dkist_header_validator-5.2.1.dist-info/WHEEL
dkist_header_validator-5.2.1.dist-info/entry_points.txt
dkist_header_validator-5.2.1.dist-info/top_level.txt
dkist_header_validator-5.2.1.dist-info/RECORD
