Metadata-Version: 2.4
Name: dkist-header-validator
Version: 5.2.1
Summary: DKIST data validator
Home-page: https://bitbucket.org/dkistdc/dkist-header-validator/src/main/
Author: NSO / AURA
Author-email: "aderks@nso.edu"
License: MIT
Classifier: Programming Language :: Python
Classifier: Programming Language :: Python :: 3
Classifier: Programming Language :: Python :: 3.10
Classifier: Programming Language :: Python :: 3.11
Requires-Python: >=3.10
Requires-Dist: astropy>=5.0
Requires-Dist: voluptuous<1.0.0,>=0.11.7
Requires-Dist: pyyaml>=6.0
Requires-Dist: dkist-fits-specifications>=4.1.0
Provides-Extra: test
Requires-Dist: pytest; extra == "test"
Requires-Dist: pytest-cov; extra == "test"
Requires-Dist: pytest-xdist; extra == "test"
Requires-Dist: deepdiff; extra == "test"
Requires-Dist: tox; extra == "test"
Requires-Dist: dkist-data-simulator; extra == "test"
Provides-Extra: cli
Requires-Dist: typer; extra == "cli"
Provides-Extra: docs
Requires-Dist: sphinx; extra == "docs"
Requires-Dist: sphinx-astropy; extra == "docs"
Requires-Dist: sphinx-changelog; extra == "docs"
Requires-Dist: sphinx-autoapi; extra == "docs"
Requires-Dist: pytest; extra == "docs"
Requires-Dist: towncrier; extra == "docs"
Requires-Dist: dkist-sphinx-theme; extra == "docs"
